LICENSE
MANIFEST.in
README.md
setup.py
./.gitlab-ci.yml
./pyPhasesRecordloaderDomino/config.yaml
pyPhasesRecordloaderDomino/Plugin.py
pyPhasesRecordloaderDomino/__init__.py
pyPhasesRecordloaderDomino/config.yaml
pyPhasesRecordloaderDomino.egg-info/PKG-INFO
pyPhasesRecordloaderDomino.egg-info/SOURCES.txt
pyPhasesRecordloaderDomino.egg-info/dependency_links.txt
pyPhasesRecordloaderDomino.egg-info/requires.txt
pyPhasesRecordloaderDomino.egg-info/top_level.txt
pyPhasesRecordloaderDomino/recordLoaders/DominoAnnotationLoader.py
pyPhasesRecordloaderDomino/recordLoaders/DominoAnnotationWriter.py
pyPhasesRecordloaderDomino/recordLoaders/DominoErgLoader.py
pyPhasesRecordloaderDomino/recordLoaders/RecordLoaderDomino.py
pyPhasesRecordloaderDomino/recordLoaders/__init__.py